tuyaha/__init__.py
tuyaha/tuyaapi.py
tuyaha/devices/__init__.py
tuyaha/devices/base.py
tuyaha/devices/climate.py
tuyaha/devices/cover.py
tuyaha/devices/factory.py
tuyaha/devices/fan.py
tuyaha/devices/light.py
tuyaha/devices/lock.py
tuyaha/devices/remote.py
tuyaha/devices/scene.py
tuyaha/devices/switch.py
tuyaha-float/__init__.py
tuyaha-float/tuyaapi.py
tuyaha-float/devices/__init__.py
tuyaha-float/devices/base.py
tuyaha-float/devices/climate.py
tuyaha-float/devices/cover.py
tuyaha-float/devices/factory.py
tuyaha-float/devices/fan.py
tuyaha-float/devices/light.py
tuyaha-float/devices/lock.py
tuyaha-float/devices/remote.py
tuyaha-float/devices/scene.py
tuyaha-float/devices/switch.py
tuyaha_float-0.0.7.dist-info/LICENSE
tuyaha_float-0.0.7.dist-info/METADATA
tuyaha_float-0.0.7.dist-info/WHEEL
tuyaha_float-0.0.7.dist-info/top_level.txt
tuyaha_float-0.0.7.dist-info/RECORD
