Metadata-Version: 2.1
Name: tuyaha-float
Version: 0.0.7
Summary: A Python library that implements a Tuya API endpoint that was specially designed for Home Assistant
Home-page: https://github.com/thepinkowl/tuyaha-float
Author: ThePinkOwl (Roger Miret Giné), Pavlo Annekov and original Tuya authors
Author-email: roger.miret@gmail.com
License: MIT
Platform: UNKNOWN
Classifier: Programming Language :: Python :: 3
Classifier: License :: OSI Approved :: MIT License
Classifier: Operating System :: OS Independent
